{
    "index": 628,
    "label": "Structured multilingual and technical content",
    "attributes": "presence of quotes, mentions of social media handles, programming language elements, multilingual content, structured like data entries",
    "reasoning": "All samples within the first set include elements such as quotes, references to social media or programming languages (as evidenced by `msgstr` and code-like syntax), colloquial speech, and multilingual content. These elements are absent from the second set. The second set mainly consists of straightforward narrative text and lacks diversity in language and context. Additionally, the first set contains elements that seem structured like data entries or documents, which is not the case in the second set.",
    "density": 0.006140238491797989,
    "confidence": 65.0,
    "high_act_samples": [
        {
            "text": "\" I don't know no Kevin.\"",
            "act": 0.2666577994823456
        },
        {
            "text": "Soc.",
            "act": 0.24259242415428162
        },
        {
            "text": "Soc.",
            "act": 0.2353074848651886
        },
        {
            "text": "Soc.",
            "act": 0.23519109189510345
        },
        {
            "text": "Soc.",
            "act": 0.23402032256126404
        },
        {
            "text": "Soc.",
            "act": 0.23347097635269165
        },
        {
            "text": "Soc.",
            "act": 0.23274008929729462
        },
        {
            "text": "Soc.",
            "act": 0.23130916059017181
        },
        {
            "text": "Soc.",
            "act": 0.2300514578819275
        },
        {
            "text": "Soc.",
            "act": 0.22987699508666992
        },
        {
            "text": "Soc.",
            "act": 0.22935612499713898
        },
        {
            "text": "Soc.",
            "act": 0.22727033495903015
        },
        {
            "text": "Soc.",
            "act": 0.22727033495903015
        },
        {
            "text": "Soc.",
            "act": 0.22727033495903015
        },
        {
            "text": "Soc.",
            "act": 0.22634033858776093
        },
        {
            "text": "Soc.",
            "act": 0.22326183319091797
        },
        {
            "text": "Soc.",
            "act": 0.22259971499443054
        },
        {
            "text": "Soc.",
            "act": 0.22259971499443054
        },
        {
            "text": "Soc.",
            "act": 0.22259971499443054
        },
        {
            "text": "Soc.",
            "act": 0.22182917594909668
        },
        {
            "text": "Soc.",
            "act": 0.22182917594909668
        },
        {
            "text": "Soc.",
            "act": 0.22130276262760162
        },
        {
            "text": "Soc.",
            "act": 0.2103903889656067
        },
        {
            "text": "Soc.",
            "act": 0.20805397629737854
        },
        {
            "text": "\"And if you don't think so, it means you prefer to do nothing!\"",
            "act": 0.20598137378692627
        },
        {
            "text": "Soc.",
            "act": 0.20486444234848022
        },
        {
            "text": "Soc.",
            "act": 0.20486444234848022
        },
        {
            "text": "\" I don't know.\"",
            "act": 0.19581249356269836
        },
        {
            "text": "Les cinq \u00e9l\u00e9ments font partie de la culture chinoise depuis presque toujours.",
            "act": 0.18602070212364197
        },
        {
            "text": "\"Come on, you must have some friend from university.\"",
            "act": 0.18198995292186737
        },
        {
            "text": "Ocular telangiectasia do not develop.",
            "act": 0.17141218483448029
        },
        {
            "text": "JPP is a top 5 DE and going into his 3rd year.",
            "act": 0.16338928043842316
        },
        {
            "text": "Riiiight.",
            "act": 0.1632930487394333
        },
        {
            "text": "msgstr \"\"\n\"Cette option d\u00e9termine les effets d'un clic du milieu sur la barre de titre \"\n\"d'une fen\u00eatre.",
            "act": 0.16035780310630798
        },
        {
            "text": "@landondonovan Come to Grand Rapids, MI.",
            "act": 0.15717658400535583
        },
        {
            "text": "\u201cLeslie is one of the toughest players in the John I Dent Cup week-in week-out, while Joe is one of the Tuggeranong Vikings top players and has a huge future in the game.",
            "act": 0.15501679480075836
        },
        {
            "text": "7 Publicado originalmente no Bulletin International de l`Academie des Sciences de Cracovie, classe d`histoire et philosophie, 1910.",
            "act": 0.15287554264068604
        },
        {
            "text": "CUP, 2011.",
            "act": 0.1498725563287735
        },
        {
            "text": "Si vous vous enregistrez dans le domain priv\u00e9 seulement les utilisateurs connect\u00e9s pourront voir la map.",
            "act": 0.14847934246063232
        },
        {
            "text": "@17 You\u2019re full of shit.",
            "act": 0.147112637758255
        },
        {
            "text": "L'empereur, hautement impressionn\u00e9 par cet exploit, lui donna la premi\u00e8re place.",
            "act": 0.14688293635845184
        },
        {
            "text": "Delimitata dalla laguna e dal mare, 232; la Venezia pi249; popolare colorata da aneddoti, ricordi e curiosit224.",
            "act": 0.14542825520038605
        },
        {
            "text": "Inverness Tickets\n\nInverness is one of the hottest football clubs in Scotland.",
            "act": 0.1449393928050995
        },
        {
            "text": "28 is used, the four-dollar ticket holder can win three dollars.",
            "act": 0.14417514204978943
        },
        {
            "text": "\"Well you wouldn't have if you hadn't gone off by yourself!\"",
            "act": 0.14374858140945435
        },
        {
            "text": "L'ensembles de donn\u00e9es associ\u00e9s n'ont aucune dimension en commun.",
            "act": 0.14354947209358215
        },
        {
            "text": "Trois syst\u00e8mes sont utilis\u00e9s pour compter et classer les ann\u00e9es : les Dix Tiges C\u00e9lestes, les Douze Rameaux Terrestres et les Douze animaux.",
            "act": 0.14354091882705688
        },
        {
            "text": "Cr\u00e8me Br\u00fbl\u00e9e\n\n4.",
            "act": 0.14324715733528137
        },
        {
            "text": "sbi.geo.controlpanel.savewin.msgDetail=S\u00e9lectionner le dossier o\u00f9 vous d\u00e9sirez publier votre map.",
            "act": 0.14273764193058014
        },
        {
            "text": "Honour\nA street of Guingamp (France) is now called \"Col. Br\u00e9bant\" to honour him.",
            "act": 0.13772223889827728
        }
    ],
    "low_act_samples": [
        {
            "text": "Can you explain your reasoning again?",
            "act": 0.0
        },
        {
            "text": "The facts seem to keep getting in the way of your theory .",
            "act": 0.0
        },
        {
            "text": ".",
            "act": 0.0
        },
        {
            "text": ".",
            "act": 0.0
        },
        {
            "text": ".",
            "act": 0.0
        },
        {
            "text": "[Bad facts!",
            "act": 0.0
        },
        {
            "text": "BAD!]",
            "act": 0.0
        },
        {
            "text": "hooray4anything\n\nWhat I'm trying to say is that nobody really knows what Oswald was doing or what he believed because he got shot too quickly to know and his motivations too murky.",
            "act": 0.0
        },
        {
            "text": "It's also hard to know because there's way too many stories out there about the whole thing but most of them do tend towards the JFK being killed as a result of him being blamed for allowing Castro to take over Cuba, whether it be the mob, anti-Castro-ites, or the CIA.",
            "act": 0.0
        },
        {
            "text": "None of those three could be considered lefty.",
            "act": 0.0
        },
        {
            "text": "So, in other words, calling Oswald one thing or another is silly because nobody knows and if there is a meme out there saying he was some crazy-ass liberal, then it shows just how desperate some people are to twist history into their weird little worldviews but facts are stubborn little things.",
            "act": 0.0
        },
        {
            "text": "fuflans\n\nsimon, please list those left wing assassinations of which you speak?",
            "act": 0.0
        },
        {
            "text": "cause i'm pretty up the news and can't think of any recent ones.",
            "act": 0.0
        },
        {
            "text": "assassinations in this country in the last 30 years have been right wing christian nutjobs, right wing islamic nutjobs and random troubled students.",
            "act": 0.0
        },
        {
            "text": "SorosBot\n\nThere's none that I can think of since the guy who killed McKinley, 110 years ago.",
            "act": 0.0
        },
        {
            "text": "Hell, the guy who shot the single right-winger who was the victim of an assassination attempt in the wave of assassinations of left-wing figures in the 60s and 70s turned out to be a nutcase who just wanted to assassinate somebody important so he would become famous; and likewise Hinkley was just an insane stalker.",
            "act": 0.0
        },
        {
            "text": "Jukesgrrl\n\nU of A basketball game scheduled for today has been canceled.",
            "act": 0.0
        },
        {
            "text": "That's as serious as shit gets here in Tucson.",
            "act": 0.0
        },
        {
            "text": "jim89048\n\nEven MSNBC stopped their weekend prison marathon to run with this, so yeah, pretty serious.",
            "act": 0.0
        },
        {
            "text": "luke_warm\n\nIt's in his second video where he talks about the constitution and \"apprehending\" the current slate of treasonous laws.",
            "act": 0.0
        },
        {
            "text": "But yeah, he's batshit.",
            "act": 0.0
        },
        {
            "text": "The judge who was assassinated was Chief Judge John Roll of the U.S. District Court for the District of Arizona.",
            "act": 0.0
        },
        {
            "text": "He had received death threats in the past from \u2026 guess!",
            "act": 0.0
        },
        {
            "text": "\u2026 talk-show listeners because he allowed a lawsuit by undocumented immigrants to go past summary judgment, and god help you if you do anything good for a Brown.",
            "act": 0.0
        },
        {
            "text": "So now we have not only had an attack on a Congresswoman (probably) because of her political affiliation but also a literal attack on judicial independence.",
            "act": 0.0
        },
        {
            "text": "In February, when U.S. District Judge John Roll presided over a $32 million civil-rights lawsuit filed by illegal immigrants against an Arizona rancher, the Marshals Service was anticipating the fallout.",
            "act": 0.0
        },
        {
            "text": "When Roll ruled the case could go forward, [Arizona U.S.",
            "act": 0.0
        },
        {
            "text": "Marshal] Gonzales said talk-radio shows cranked up the controversy and spurred audiences into making threats.",
            "act": 0.0
        },
        {
            "text": "In one afternoon, Roll logged more than 200 phone calls.",
            "act": 0.0
        },
        {
            "text": "Callers threatened the judge and his family.",
            "act": 0.0
        },
        {
            "text": "They posted personal information about Roll online.",
            "act": 0.0
        },
        {
            "text": "\"They said, 'We should kill him.",
            "act": 0.0
        },
        {
            "text": "He should be dead,' \" Gonzales said.",
            "act": 0.0
        },
        {
            "text": "Roll, who is the chief federal judge in Arizona, said both he and his wife were given a protection detail for about a month.",
            "act": 0.0
        },
        {
            "text": "\"It was unnerving and invasive.",
            "act": 0.0
        },
        {
            "text": ".",
            "act": 0.0
        },
        {
            "text": ".",
            "act": 0.0
        },
        {
            "text": ".",
            "act": 0.0
        },
        {
            "text": "By its nature it has to be,\" Roll said, adding that they were encouraged to live their lives as normally as possible.",
            "act": 0.0
        },
        {
            "text": "\"It was handled very professionally by the Marshals Service.\"",
            "act": 0.0
        },
        {
            "text": "At the end of the month, Roll said four key men had been identified as threat makers.",
            "act": 0.0
        },
        {
            "text": "The Marshals Service left to him the decision to press charges but recommended against it.",
            "act": 0.0
        },
        {
            "text": "Roll said he had no qualms about following their advice.",
            "act": 0.0
        },
        {
            "text": "AZ_Transplant\n\nI worked in her office last year.",
            "act": 0.0
        },
        {
            "text": "I only met her a few times, but she she was always really genuine and kind.",
            "act": 0.0
        },
        {
            "text": "I hope she pulls through.",
            "act": 0.0
        },
        {
            "text": "It's not a particularly common name, is it?",
            "act": 0.0
        },
        {
            "text": "Photo must be from 2010 festival, since the 2011 one is not scheduled until March.",
            "act": 0.0
        },
        {
            "text": "karen\n\nYeah that's what I was thinking.",
            "act": 0.0
        },
        {
            "text": "EdFlintstone\n\nSarah save your bullshit sympathy post on fucking facebook.",
            "act": 0.0
        }
    ]
}