{
    "index": 531,
    "label": "Informative and factual content",
    "attributes": "informative content, structured format, factual information, diverse topics, descriptive language",
    "reasoning": "The samples contain informative, structured content that spans a variety of subjects such as finance, culture, history, technology, and general knowledge. They often present factual information, descriptions, or explanations. This is contrasted with the other samples which contain opinionated, conversational, and context-specific discussions.",
    "density": 0.006866248143455711,
    "confidence": 10.0,
    "high_act_samples": [
        {
            "text": "msgstr \"\u062f\u0631 \u0635\u0648\u0631\u062a \u0628\u0631\u0631\u0633\u06cc \u060c \u0628\u0631\u062e\u06cc \u067e\u06cc\u0627\u0645 \u0647\u0627 \u062e\u0637\u0627\u06cc \u062a\u062d\u0648\u06cc\u0644 \u062f\u0627\u0631\u0646\u062f.\"",
            "act": 0.27120503783226013
        },
        {
            "text": "Heat?",
            "act": 0.25570809841156006
        },
        {
            "text": "msgstr \"\"\n\"\u0627\u06af\u0631 \u0627\u06cc\u0646 \u06af\u0632\u06cc\u0646\u0647 \u0631\u0627 \u0627\u0646\u062a\u062e\u0627\u0628 \u06a9\u0646\u06cc\u062f\u060c \u067e\u06cc\u0627\u0645\u200c\u0647\u0627\u06cc \u062c\u062f\u06cc\u062f \u0628\u0647 \u062a\u0648\u062c\u0647 \u0634\u0645\u0627 \u0646\u06cc\u0627\u0632 \u062e\u0648\u0627\u0647\u0646\u062f \u062f\u0627\u0634\u062a.\"",
            "act": 0.22569194436073303
        },
        {
            "text": "Strange Aircraft?",
            "act": 0.19483891129493713
        },
        {
            "text": "WebRhythms is a series of short articles designed to teach rhythmic reading.",
            "act": 0.16572876274585724
        },
        {
            "text": "Applying promotion strategies to campaigns dates to a \u201cMad Men\u201d epoch of a 1960s.",
            "act": 0.16026714444160461
        },
        {
            "text": "A Semi-Whole Foods Slow Cooker Cookbook by Stacy Myers features 40 all-original slow cooker recipes covering everything from soups to desserts.",
            "act": 0.16001848876476288
        },
        {
            "text": "Is China?",
            "act": 0.15680892765522003
        },
        {
            "text": "\"No, no, no, no, no.\"",
            "act": 0.15539519488811493
        },
        {
            "text": "The Crown Colonies are companies owned by the British Monarchs and other royal families that do business inside of the City of London Corporation.",
            "act": 0.149744912981987
        },
        {
            "text": "On the sales side, the job involves getting contracts to supply power.",
            "act": 0.14777864515781403
        },
        {
            "text": "The concepts of \u201cchristian\u201d punk, \u201cislamic\u201d punk make no sense to me.",
            "act": 0.14059647917747498
        },
        {
            "text": "Many people like to invest in stock market with their own set of reasons.",
            "act": 0.13814358413219452
        },
        {
            "text": "Anan is a fresh, adorable, and cute Muslim girl name, meaning \u2018cloud\u2019.",
            "act": 0.13727551698684692
        },
        {
            "text": "These practices include silent illumination and huatou practice.",
            "act": 0.13612806797027588
        },
        {
            "text": "It is driven with two petrol aerial engines of from 50 to 60 horse-power.",
            "act": 0.13478997349739075
        },
        {
            "text": "Op-eds\n\nCorporate Investments Can Help Accelerate Economic Growth in the Developing World: Op-Ed by Ambassador Bloomfield (F80)\n\nMany people assume that foreign aid from governments and international bodies is the key driver of economic growth and modernization in much of the developing world.",
            "act": 0.13475234806537628
        },
        {
            "text": "There is a myth in American politics about elected officials and private businesses.",
            "act": 0.13282334804534912
        },
        {
            "text": "Politicians have been coming here ever since elections were announced with promises to bring power supply and roads.",
            "act": 0.12682709097862244
        },
        {
            "text": "Types of Account \nFirst United Bank offers many different types of checking and savings accounts.",
            "act": 0.12070170789957047
        },
        {
            "text": "Corporations are racing to take advantage of debt financing before rates rise.",
            "act": 0.11624421924352646
        },
        {
            "text": "Old silver coins!",
            "act": 0.115431047976017
        },
        {
            "text": "SciTim,\nAnonymous and pseudonymous writing is a time honored American tradition.",
            "act": 0.11476245522499084
        },
        {
            "text": "Variables   Num.",
            "act": 0.1147264912724495
        },
        {
            "text": "The Internet Corporation for Assigned Names and Numbers, unknown to many internet users, is a non-profit organization based in the US.",
            "act": 0.1137358695268631
        },
        {
            "text": "How long?",
            "act": 0.11247731000185013
        },
        {
            "text": "Wu Teh Yao\n\nWu Teh Yao (, 1915\u201317 April 1994) was a Chinese political scientist.",
            "act": 0.11178721487522125
        },
        {
            "text": "Algerian Hostage Tapes: Inside Intel on Terror Attack?",
            "act": 0.11158285290002823
        },
        {
            "text": "msgstr \"\u0627\u0631\u0632 \u0627\u0635\u0644\u06cc \u0634\u0631\u06a9\u062a\"\n\n#.",
            "act": 0.11151789873838425
        },
        {
            "text": "due to network connectivity.",
            "act": 0.11061859130859375
        },
        {
            "text": "9\nWhat is ((-1919)/190 + 10)/1?",
            "act": 0.11019090563058853
        },
        {
            "text": "Hundreds of calls and emails and Bank of America continues to amaze me!",
            "act": 0.1101086214184761
        },
        {
            "text": "The British royal family uses these universities to recruit their Crown Agents who then serve their interests by infiltrating corporate and government agencies.",
            "act": 0.10956620424985886
        },
        {
            "text": "Tornadoes?",
            "act": 0.10948257148265839
        },
        {
            "text": "Crises of gridlock, such as the recent showdown over the debt ceiling, have become common.",
            "act": 0.10892388969659805
        },
        {
            "text": "Muslim name Falak means \u2018sky is full light and is beautiful\u2019.",
            "act": 0.10760007798671722
        },
        {
            "text": "The context of the verse \n\u064a\u064e\u0627 \u0623\u064e\u064a\u064f\u0651\u0647\u064e\u0627 \u0627\u0644\u064e\u0651\u0630\u0650\u064a\u0646\u064e \u0622\u0645\u064e\u0646\u064f\u0648\u0627 \u0625\u0650\u0630\u064e\u0627 \u062a\u064e\u062f\u064e\u0627\u064a\u064e\u0646\u062a\u064f\u0645 \u0628\u0650\u062f\u064e\u064a\u0652\u0646\u064d \u0625\u0650\u0644\u064e\u0649\u0670 \u0623\u064e\u062c\u064e\u0644\u064d \u0645\u064f\u0651\u0633\u064e\u0645\u064b\u0651\u0649 \u0641\u064e\u0627\u0643\u0652\u062a\u064f\u0628\u064f\u0648\u0647\u064f \u06da\u0648\u064e\u0644\u0652\u064a\u064e\u0643\u0652\u062a\u064f\u0628 \u0628\u064e\u0651\u064a\u0652\u0646\u064e\u0643\u064f\u0645\u0652 \u0643\u064e\u0627\u062a\u0650\u0628\u064c \u0628\u0650\u0627\u0644\u0652\u0639\u064e\u062f\u0652\u0644\u0650 \u06da \u0648\u064e\u0644\u064e\u0627 \u064a\u064e\u0623\u0652\u0628\u064e \u0643\u064e\u0627\u062a\u0650\u0628\u064c \u0623\u064e\u0646 \u064a\u064e\u0643\u0652\u062a\u064f\u0628\u064e \u0643\u064e\u0645\u064e\u0627 \u0639\u064e\u0644\u064e\u0651\u0645\u064e\u0647\u064f \u0627\u0644\u0644\u064e\u0651\u0640\u0647\u064f \u06da \u0641\u064e\u0644\u0652\u064a\u064e\u0643\u0652\u062a\u064f\u0628\u0652 \u0648\u064e\u0644\u0652\u064a\u064f\u0645\u0652\u0644\u0650\u0644\u0650 \u0627\u0644\u064e\u0651\u0630\u0650\u064a \u0639\u064e\u0644\u064e\u064a\u0652\u0647\u0650 \u0627\u0644\u0652\u062d\u064e\u0642\u064f\u0651 \u0648\u064e\u0644\u0652\u064a\u064e\u062a\u064e\u0651\u0642\u0650 \u0627\u0644\u0644\u064e\u0651\u0640\u0647\u064e \u0631\u064e\u0628\u064e\u0651\u0647\u064f \u0648\u064e\u0644\u064e\u0627 \u064a\u064e\u0628\u0652\u062e\u064e\u0633\u0652 \u0645\u0650\u0646\u0652\u0647\u064f \u0634\u064e\u064a\u0652\u0626\u064b\u0627 \u06da \u0641\u064e\u0625\u0650\u0646 \u0643\u064e\u0627\u0646\u064e \u0627\u0644\u064e\u0651\u0630\u0650\u064a \u0639\u064e\u0644\u064e\u064a\u0652\u0647\u0650 \u0627\u0644\u0652\u062d\u064e\u0642\u064f\u0651 \u0633\u064e\u0641\u0650\u064a\u0647\u064b\u0627 \u0623\u064e\u0648\u0652 \u0636\u064e\u0639\u0650\u064a\u0641\u064b\u0627 \u0623\u064e\u0648\u0652 \u0644\u064e\u0627 \u064a\u064e\u0633\u0652\u062a\u064e\u0637\u0650\u064a\u0639\u064f \u0623\u064e\u0646 \u064a\u064f\u0645\u0650\u0644\u064e\u0651 \u0647\u064f\u0648\u064e \u0641\u064e\u0644\u0652\u064a\u064f\u0645\u0652\u0644\u0650\u0644\u0652 \u0648\u064e\u0644\u0650\u064a\u064f\u0651\u0647\u064f \u0628\u0650\u0627\u0644\u0652\u0639\u064e\u062f\u0652\u0644\u0650 \u06da \u0648\u064e\u0627\u0633\u0652\u062a\u064e\u0634\u0652\u0647\u0650\u062f\u064f\u0648\u0627 \u0634\u064e\u0647\u0650\u064a\u062f\u064e\u064a\u0652\u0646\u0650 \u0645\u0650\u0646 \u0631\u0650\u0651\u062c\u064e\u0627\u0644\u0650\u0643\u064f\u0645\u0652 \u06d6 \u0641\u064e\u0625\u0650\u0646 \u0644\u064e\u0651\u0645\u0652 \u064a\u064e\u0643\u064f\u0648\u0646\u064e\u0627 \u0631\u064e\u062c\u064f\u0644\u064e\u064a\u0652\u0646\u0650 \u0641\u064e\u0631\u064e\u062c\u064f\u0644\u064c \u0648\u064e\u0627\u0645\u0652\u0631\u064e\u0623\u064e\u062a\u064e\u0627\u0646\u0650 \u0645\u0650\u0645\u064e\u0651\u0646 \u062a\u064e\u0631\u0652\u0636\u064e\u0648\u0652\u0646\u064e \u0645\u0650\u0646\u064e \u0627\u0644\u0634\u064f\u0651\u0647\u064e\u062f\u064e\u0627\u0621\u0650 \u0623\u064e\u0646 \u062a\u064e\u0636\u0650\u0644\u064e\u0651 \u0625\u0650\u062d\u0652\u062f\u064e\u0627\u0647\u064f\u0645\u064e\u0627 \u0641\u064e\u062a\u064f\u0630\u064e\u0643\u0650\u0651\u0631\u064e \u0625\u0650\u062d\u0652\u062f\u064e\u0627\u0647\u064f\u0645\u064e\u0627 \u0627\u0644\u0652\u0623\u064f\u062e\u0652\u0631\u064e\u0649\u0670 \u06da \u0648\u064e\u0644\u064e\u0627 \u064a\u064e\u0623\u0652\u0628\u064e \u0627\u0644\u0634\u064f\u0651\u0647\u064e\u062f\u064e\u0627\u0621\u064f \u0625\u0650\u0630\u064e\u0627 \u0645\u064e\u0627 \u062f\u064f\u0639\u064f\u0648\u0627 \u06da \u0648\u064e\u0644\u064e\u0627 \u062a\u064e\u0633\u0652\u0623\u064e\u0645\u064f\u0648\u0627 \u0623\u064e\u0646 \u062a\u064e\u0643\u0652\u062a\u064f\u0628\u064f\u0648\u0647\u064f \u0635\u064e\u063a\u0650\u064a\u0631\u064b\u0627 \u0623\u064e\u0648\u0652 \u0643\u064e\u0628\u0650\u064a\u0631\u064b\u0627 \u0625\u0650\u0644\u064e\u0649\u0670 \u0623\u064e\u062c\u064e\u0644\u0650\u0647\u0650 \u06da \u0630\u064e\u0670\u0644\u0650\u0643\u064f\u0645\u0652 \u0623\u064e\u0642\u0652\u0633\u064e\u0637\u064f \u0639\u0650\u0646\u062f\u064e \u0627\u0644\u0644\u064e\u0651\u0640\u0647\u0650 \u0648\u064e\u0623\u064e\u0642\u0652\u0648\u064e\u0645\u064f \u0644\u0650\u0644\u0634\u064e\u0651\u0647\u064e\u0627\u062f\u064e\u0629\u0650 \u0648\u064e\u0623\u064e\u062f\u0652\u0646\u064e\u0649\u0670 \u0623\u064e\u0644\u064e\u0651\u0627 \u062a\u064e\u0631\u0652\u062a\u064e\u0627\u0628\u064f\u0648\u0627 \u06d6 \u0625\u0650\u0644\u064e\u0651\u0627 \u0623\u064e\u0646 \u062a\u064e\u0643\u064f\u0648\u0646\u064e \u062a\u0650\u062c\u064e\u0627\u0631\u064e\u0629\u064b \u062d\u064e\u0627\u0636\u0650\u0631\u064e\u0629\u064b \u062a\u064f\u062f\u0650\u064a\u0631\u064f\u0648\u0646\u064e\u0647\u064e\u0627 \u0628\u064e\u064a\u0652\u0646\u064e\u0643\u064f\u0645\u0652 \u0641\u064e\u0644\u064e\u064a\u0652\u0633\u064e \u0639\u064e\u0644\u064e\u064a\u0652\u0643\u064f\u0645\u0652 \u062c\u064f\u0646\u064e\u0627\u062d\u064c \u0623\u064e\u0644\u064e\u0651\u0627 \u062a\u064e\u0643\u0652\u062a\u064f\u0628\u064f\u0648\u0647\u064e\u0627 \u06d7 \u0648\u064e\u0623\u064e\u0634\u0652\u0647\u0650\u062f\u064f\u0648\u0627 \u0625\u0650\u0630\u064e\u0627 \u062a\u064e\u0628\u064e\u0627\u064a\u064e\u0639\u0652\u062a\u064f\u0645\u0652 \u06da \u0648\u064e\u0644\u064e\u0627 \u064a\u064f\u0636\u064e\u0627\u0631\u064e\u0651 \u0643\u064e\u0627\u062a\u0650\u0628\u064c \u0648\u064e\u0644\u064e\u0627 \u0634\u064e\u0647\u0650\u064a\u062f\u064c \u06da \u0648\u064e\u0625\u0650\u0646 \u062a\u064e\u0641\u0652\u0639\u064e\u0644\u064f\u0648\u0627 \u0641\u064e\u0625\u0650\u0646\u064e\u0651\u0647\u064f \u0641\u064f\u0633\u064f\u0648\u0642\u064c \u0628\u0650\u0643\u064f\u0645\u0652 \u06d7 \u0648\u064e\u0627\u062a\u064e\u0651\u0642\u064f\u0648\u0627 \u0627\u0644\u0644\u064e\u0651\u0640\u0647\u064e \u06d6 \u0648\u064e\u064a\u064f\u0639\u064e\u0644\u0650\u0651\u0645\u064f\u0643\u064f\u0645\u064f \u0627\u0644\u0644\u064e\u0651\u0640\u0647\u064f \u06d7 \u0648\u064e\u0627\u0644\u0644\u064e\u0651\u0640\u0647\u064f \u0628\u0650\u0643\u064f\u0644\u0650\u0651 \u0634\u064e\u064a\u0652\u0621\u064d \u0639\u064e\u0644\u0650\u064a\u0645\u064c \n\nO ye who believe!",
            "act": 0.10674742609262466
        },
        {
            "text": "EnglishCast: The Lord Family \u2013 This documentary investigates song and music in the context of the Indian filmic experience.",
            "act": 0.1052883192896843
        },
        {
            "text": "// How to prevent it?",
            "act": 0.10476285964250565
        },
        {
            "text": "Tea and Crumpets is a new book by Margaret M. Johnson .",
            "act": 0.10156933218240738
        },
        {
            "text": "Twenty years ago images of Ethiopia were beamed into our living rooms and showed people in poor countries living with overwhelming poverty, disease, and despair.",
            "act": 0.10147292166948318
        },
        {
            "text": "HubSpot is betting on content marketing and personalized experiences.",
            "act": 0.09946259111166
        },
        {
            "text": "Delicious food, intriguing architecture, wonderful people, diverse hikes, and soaring waterfalls.",
            "act": 0.09910327941179276
        },
        {
            "text": "Pembrokeshire is a place of magic, mystery & enchantment with wild landscapes, imbued with five-thousand years of deeply layered history and culture.",
            "act": 0.09803073108196259
        },
        {
            "text": "The \u201cDisney playground\u201d?",
            "act": 0.09653244912624359
        },
        {
            "text": "Classic \u201cbooks of creed\u201d all warn against causing social upheaval.",
            "act": 0.09637167304754257
        },
        {
            "text": "The Iraq\nWar has given rise to a number of contradictory stories about women in Iraq.",
            "act": 0.09605009853839874
        },
        {
            "text": "The Occupy movement started in New York in September as a call to action against unequal wealth distribution.",
            "act": 0.09570438414812088
        },
        {
            "text": "Description\n\nFour Horses is a tiny independent self-publishing video game developer with a love for classic video games and portable gaming.",
            "act": 0.09569326788187027
        },
        {
            "text": "Warships, plains, British Airways Concorde, helicopters and more to see.",
            "act": 0.09553235024213791
        }
    ],
    "low_act_samples": [
        {
            "text": "Can you explain your reasoning again?",
            "act": 0.0
        },
        {
            "text": "The facts seem to keep getting in the way of your theory .",
            "act": 0.0
        },
        {
            "text": ".",
            "act": 0.0
        },
        {
            "text": ".",
            "act": 0.0
        },
        {
            "text": ".",
            "act": 0.0
        },
        {
            "text": "[Bad facts!",
            "act": 0.0
        },
        {
            "text": "BAD!]",
            "act": 0.0
        },
        {
            "text": "hooray4anything\n\nWhat I'm trying to say is that nobody really knows what Oswald was doing or what he believed because he got shot too quickly to know and his motivations too murky.",
            "act": 0.0
        },
        {
            "text": "It's also hard to know because there's way too many stories out there about the whole thing but most of them do tend towards the JFK being killed as a result of him being blamed for allowing Castro to take over Cuba, whether it be the mob, anti-Castro-ites, or the CIA.",
            "act": 0.0
        },
        {
            "text": "None of those three could be considered lefty.",
            "act": 0.0
        },
        {
            "text": "So, in other words, calling Oswald one thing or another is silly because nobody knows and if there is a meme out there saying he was some crazy-ass liberal, then it shows just how desperate some people are to twist history into their weird little worldviews but facts are stubborn little things.",
            "act": 0.0
        },
        {
            "text": "fuflans\n\nsimon, please list those left wing assassinations of which you speak?",
            "act": 0.0
        },
        {
            "text": "cause i'm pretty up the news and can't think of any recent ones.",
            "act": 0.0
        },
        {
            "text": "assassinations in this country in the last 30 years have been right wing christian nutjobs, right wing islamic nutjobs and random troubled students.",
            "act": 0.0
        },
        {
            "text": "SorosBot\n\nThere's none that I can think of since the guy who killed McKinley, 110 years ago.",
            "act": 0.0
        },
        {
            "text": "Hell, the guy who shot the single right-winger who was the victim of an assassination attempt in the wave of assassinations of left-wing figures in the 60s and 70s turned out to be a nutcase who just wanted to assassinate somebody important so he would become famous; and likewise Hinkley was just an insane stalker.",
            "act": 0.0
        },
        {
            "text": "Jukesgrrl\n\nU of A basketball game scheduled for today has been canceled.",
            "act": 0.0
        },
        {
            "text": "That's as serious as shit gets here in Tucson.",
            "act": 0.0
        },
        {
            "text": "jim89048\n\nEven MSNBC stopped their weekend prison marathon to run with this, so yeah, pretty serious.",
            "act": 0.0
        },
        {
            "text": "luke_warm\n\nIt's in his second video where he talks about the constitution and \"apprehending\" the current slate of treasonous laws.",
            "act": 0.0
        },
        {
            "text": "But yeah, he's batshit.",
            "act": 0.0
        },
        {
            "text": "The judge who was assassinated was Chief Judge John Roll of the U.S. District Court for the District of Arizona.",
            "act": 0.0
        },
        {
            "text": "He had received death threats in the past from \u2026 guess!",
            "act": 0.0
        },
        {
            "text": "\u2026 talk-show listeners because he allowed a lawsuit by undocumented immigrants to go past summary judgment, and god help you if you do anything good for a Brown.",
            "act": 0.0
        },
        {
            "text": "So now we have not only had an attack on a Congresswoman (probably) because of her political affiliation but also a literal attack on judicial independence.",
            "act": 0.0
        },
        {
            "text": "In February, when U.S. District Judge John Roll presided over a $32 million civil-rights lawsuit filed by illegal immigrants against an Arizona rancher, the Marshals Service was anticipating the fallout.",
            "act": 0.0
        },
        {
            "text": "When Roll ruled the case could go forward, [Arizona U.S.",
            "act": 0.0
        },
        {
            "text": "Marshal] Gonzales said talk-radio shows cranked up the controversy and spurred audiences into making threats.",
            "act": 0.0
        },
        {
            "text": "In one afternoon, Roll logged more than 200 phone calls.",
            "act": 0.0
        },
        {
            "text": "Callers threatened the judge and his family.",
            "act": 0.0
        },
        {
            "text": "They posted personal information about Roll online.",
            "act": 0.0
        },
        {
            "text": "\"They said, 'We should kill him.",
            "act": 0.0
        },
        {
            "text": "He should be dead,' \" Gonzales said.",
            "act": 0.0
        },
        {
            "text": "Roll, who is the chief federal judge in Arizona, said both he and his wife were given a protection detail for about a month.",
            "act": 0.0
        },
        {
            "text": "\"It was unnerving and invasive.",
            "act": 0.0
        },
        {
            "text": ".",
            "act": 0.0
        },
        {
            "text": ".",
            "act": 0.0
        },
        {
            "text": ".",
            "act": 0.0
        },
        {
            "text": "By its nature it has to be,\" Roll said, adding that they were encouraged to live their lives as normally as possible.",
            "act": 0.0
        },
        {
            "text": "\"It was handled very professionally by the Marshals Service.\"",
            "act": 0.0
        },
        {
            "text": "At the end of the month, Roll said four key men had been identified as threat makers.",
            "act": 0.0
        },
        {
            "text": "The Marshals Service left to him the decision to press charges but recommended against it.",
            "act": 0.0
        },
        {
            "text": "Roll said he had no qualms about following their advice.",
            "act": 0.0
        },
        {
            "text": "AZ_Transplant\n\nI worked in her office last year.",
            "act": 0.0
        },
        {
            "text": "I only met her a few times, but she she was always really genuine and kind.",
            "act": 0.0
        },
        {
            "text": "I hope she pulls through.",
            "act": 0.0
        },
        {
            "text": "It's not a particularly common name, is it?",
            "act": 0.0
        },
        {
            "text": "Photo must be from 2010 festival, since the 2011 one is not scheduled until March.",
            "act": 0.0
        },
        {
            "text": "karen\n\nYeah that's what I was thinking.",
            "act": 0.0
        },
        {
            "text": "EdFlintstone\n\nSarah save your bullshit sympathy post on fucking facebook.",
            "act": 0.0
        }
    ]
}