{
    "index": 224,
    "label": "Has formal and structured content",
    "attributes": "academic citations, formal numerical data, mixed languages, formal references, technical content",
    "reasoning": "Upon carefully examining the texts within the two sets of samples, it is clear that the positive set contains complex information and formal references, such as academic citations, temperature values, programming code, and structured lists. These texts come from a variety of contexts and styles, including scientific, legal, and technical. On the other hand, the negative samples consist mostly of informal text, commentary, opinions, and conversational text. They lack citations, structured numerical data, and formal references.",
    "density": 0.010164135123208108,
    "confidence": 95.0,
    "high_act_samples": [
        {
            "text": "Marie, Ontario",
            "act": 0.28822994232177734
        },
        {
            "text": "(Normalized to unity.",
            "act": 0.2701578438282013
        },
        {
            "text": "\"Everything's going to blow up.\"",
            "act": 0.23258742690086365
        },
        {
            "text": "She\nhisses and her face warps into a malformed spotted thing.",
            "act": 0.22017179429531097
        },
        {
            "text": "(The value given in Ref.",
            "act": 0.2200426161289215
        },
        {
            "text": "Again (cf.",
            "act": 0.202666774392128
        },
        {
            "text": "(An explanation immediately leapt to my mind.",
            "act": 0.19990010559558868
        },
        {
            "text": "The MCDS operation (*t*~1~ and *t*~2~ in Fig.",
            "act": 0.19956526160240173
        },
        {
            "text": "(Pet.",
            "act": 0.1935569941997528
        },
        {
            "text": "at 15 (citing Wisc.",
            "act": 0.19118618965148926
        },
        {
            "text": "Giusto il tempo di architettare la trattativa con la per Higuain e altre due operazioni, ma il lavoro che vogliono svolgere in casa rossonera \u00e8 molto pi\u00f9 grande.",
            "act": 0.19061872363090515
        },
        {
            "text": "Paredes ha un costo elevato, e lo Zenit non vorrebbe perderlo dopo l\u2019acquisizione a luglio 2017 per circa 25 milioni di euro.",
            "act": 0.18928861618041992
        },
        {
            "text": "(1993 Cum.",
            "act": 0.1875404566526413
        },
        {
            "text": "She was still in bed but her eyes were open.",
            "act": 0.1809111386537552
        },
        {
            "text": "(1993 Cum.",
            "act": 0.17605838179588318
        },
        {
            "text": "(Chambers, supra, 410 U.S. at p.",
            "act": 0.17443814873695374
        },
        {
            "text": "(illustrated in FIG.",
            "act": 0.17339158058166504
        },
        {
            "text": "He's just popping off his mouth.",
            "act": 0.17337898910045624
        },
        {
            "text": "Spotted Puffbird came quite easily (and close!",
            "act": 0.17253240942955017
        },
        {
            "text": "Bundesliga S\u00fcd (the southern division of 2.",
            "act": 0.17231956124305725
        },
        {
            "text": "Si ragiona quindi su cifre pi\u00f9 alte, che il Milan non potr\u00e0 spendere cos\u00ec facilmente, soprattutto se non vorr\u00e0 far 'innervosire' la UEFA.",
            "act": 0.1675335168838501
        },
        {
            "text": "To implement the global chopper stabilization, the procedure above is repeated (*t*~5~ to *t*~8~ in Fig.",
            "act": 0.16696858406066895
        },
        {
            "text": "Go to Settings \u2013 Settings manager \u2013 Session and startup.",
            "act": 0.16582003235816956
        },
        {
            "text": "By Heron\u2019s theorem (Thm.",
            "act": 0.16580024361610413
        },
        {
            "text": "(citing Miss.",
            "act": 0.16557949781417847
        },
        {
            "text": "(Some signals are not shown in FIG.",
            "act": 0.16441664099693298
        },
        {
            "text": "The thought horrifies me.",
            "act": 0.16339805722236633
        },
        {
            "text": "(See Pls.'",
            "act": 0.16319787502288818
        },
        {
            "text": "@\"Oranges\" : (_grapes.count ?",
            "act": 0.16304799914360046
        },
        {
            "text": "@\"Oranges\" : (_grapes.count ?",
            "act": 0.16304799914360046
        },
        {
            "text": "Con DAZN vedi oltre 100 match di Serie A in esclusiva e tutta la Serie B IN STREAMING, LIVE E ON DEMAND\n\nMotivo per il quale sono gi\u00e0 a lavoro per le prossime sessioni di mercato di gennaio e di giugno.",
            "act": 0.16247239708900452
        },
        {
            "text": "(Evid.",
            "act": 0.1622762680053711
        },
        {
            "text": "\u00a7 405 (Supp.",
            "act": 0.16101130843162537
        },
        {
            "text": "(Ibid.",
            "act": 0.16074226796627045
        },
        {
            "text": "Gen. Laws 317, 441 (Tex.Code Crim.",
            "act": 0.15912514925003052
        },
        {
            "text": "(See id.",
            "act": 0.1589811146259308
        },
        {
            "text": "map (oneAttr .",
            "act": 0.15882816910743713
        },
        {
            "text": "(The average consumer spends just under $1,000 annually with Amazon.",
            "act": 0.15872299671173096
        },
        {
            "text": "157.8--159.4 \u00b0C (decomp.",
            "act": 0.15810754895210266
        },
        {
            "text": "\"What's going to stop us?\"",
            "act": 0.15797019004821777
        },
        {
            "text": "CoreScore A score from 1 to 100 that summarizes opinions from users and experts.",
            "act": 0.1574159413576126
        },
        {
            "text": "152.8--154.8 \u00b0C (decomp.",
            "act": 0.15642958879470825
        },
        {
            "text": "@\"Apples\" : (_oranges.count ?",
            "act": 0.15511178970336914
        },
        {
            "text": "T\u00e1mogasd te is a f\u00fcggetlen \u00fajs\u00e1g\u00edr\u00e1st, hogy ebben a neh\u00e9z helyzetben is tov\u00e1bb dolgozhassunk!",
            "act": 0.1549111306667328
        },
        {
            "text": "(App.",
            "act": 0.15462951362133026
        },
        {
            "text": "Oranges : (_grapes.count ?",
            "act": 0.15457911789417267
        },
        {
            "text": "#BREAKING: Harris County TX emergency mgmt says hundreds of homes are now flooded in western part of county.",
            "act": 0.15362924337387085
        },
        {
            "text": "Apples : (_oranges.count ?",
            "act": 0.15318533778190613
        },
        {
            "text": "Section 45 (Ill. Rev.",
            "act": 0.15120768547058105
        },
        {
            "text": "*/\n\tpublic ReactiveMongoQueryMethod(Method method, RepositoryMetadata metadata, ProjectionFactory projectionFactory,\n\t\t\tMappingContext<?",
            "act": 0.15077368915081024
        }
    ],
    "low_act_samples": [
        {
            "text": "Can you explain your reasoning again?",
            "act": 0.0
        },
        {
            "text": "The facts seem to keep getting in the way of your theory .",
            "act": 0.0
        },
        {
            "text": ".",
            "act": 0.0
        },
        {
            "text": ".",
            "act": 0.0
        },
        {
            "text": ".",
            "act": 0.0
        },
        {
            "text": "[Bad facts!",
            "act": 0.0
        },
        {
            "text": "BAD!]",
            "act": 0.0
        },
        {
            "text": "hooray4anything\n\nWhat I'm trying to say is that nobody really knows what Oswald was doing or what he believed because he got shot too quickly to know and his motivations too murky.",
            "act": 0.0
        },
        {
            "text": "It's also hard to know because there's way too many stories out there about the whole thing but most of them do tend towards the JFK being killed as a result of him being blamed for allowing Castro to take over Cuba, whether it be the mob, anti-Castro-ites, or the CIA.",
            "act": 0.0
        },
        {
            "text": "None of those three could be considered lefty.",
            "act": 0.0
        },
        {
            "text": "So, in other words, calling Oswald one thing or another is silly because nobody knows and if there is a meme out there saying he was some crazy-ass liberal, then it shows just how desperate some people are to twist history into their weird little worldviews but facts are stubborn little things.",
            "act": 0.0
        },
        {
            "text": "fuflans\n\nsimon, please list those left wing assassinations of which you speak?",
            "act": 0.0
        },
        {
            "text": "cause i'm pretty up the news and can't think of any recent ones.",
            "act": 0.0
        },
        {
            "text": "assassinations in this country in the last 30 years have been right wing christian nutjobs, right wing islamic nutjobs and random troubled students.",
            "act": 0.0
        },
        {
            "text": "SorosBot\n\nThere's none that I can think of since the guy who killed McKinley, 110 years ago.",
            "act": 0.0
        },
        {
            "text": "Hell, the guy who shot the single right-winger who was the victim of an assassination attempt in the wave of assassinations of left-wing figures in the 60s and 70s turned out to be a nutcase who just wanted to assassinate somebody important so he would become famous; and likewise Hinkley was just an insane stalker.",
            "act": 0.0
        },
        {
            "text": "Jukesgrrl\n\nU of A basketball game scheduled for today has been canceled.",
            "act": 0.0
        },
        {
            "text": "That's as serious as shit gets here in Tucson.",
            "act": 0.0
        },
        {
            "text": "jim89048\n\nEven MSNBC stopped their weekend prison marathon to run with this, so yeah, pretty serious.",
            "act": 0.0
        },
        {
            "text": "luke_warm\n\nIt's in his second video where he talks about the constitution and \"apprehending\" the current slate of treasonous laws.",
            "act": 0.0
        },
        {
            "text": "But yeah, he's batshit.",
            "act": 0.0
        },
        {
            "text": "The judge who was assassinated was Chief Judge John Roll of the U.S. District Court for the District of Arizona.",
            "act": 0.0
        },
        {
            "text": "He had received death threats in the past from \u2026 guess!",
            "act": 0.0
        },
        {
            "text": "\u2026 talk-show listeners because he allowed a lawsuit by undocumented immigrants to go past summary judgment, and god help you if you do anything good for a Brown.",
            "act": 0.0
        },
        {
            "text": "So now we have not only had an attack on a Congresswoman (probably) because of her political affiliation but also a literal attack on judicial independence.",
            "act": 0.0
        },
        {
            "text": "In February, when U.S. District Judge John Roll presided over a $32 million civil-rights lawsuit filed by illegal immigrants against an Arizona rancher, the Marshals Service was anticipating the fallout.",
            "act": 0.0
        },
        {
            "text": "When Roll ruled the case could go forward, [Arizona U.S.",
            "act": 0.0
        },
        {
            "text": "Marshal] Gonzales said talk-radio shows cranked up the controversy and spurred audiences into making threats.",
            "act": 0.0
        },
        {
            "text": "In one afternoon, Roll logged more than 200 phone calls.",
            "act": 0.0
        },
        {
            "text": "Callers threatened the judge and his family.",
            "act": 0.0
        },
        {
            "text": "They posted personal information about Roll online.",
            "act": 0.0
        },
        {
            "text": "\"They said, 'We should kill him.",
            "act": 0.0
        },
        {
            "text": "He should be dead,' \" Gonzales said.",
            "act": 0.0
        },
        {
            "text": "Roll, who is the chief federal judge in Arizona, said both he and his wife were given a protection detail for about a month.",
            "act": 0.0
        },
        {
            "text": "\"It was unnerving and invasive.",
            "act": 0.0
        },
        {
            "text": ".",
            "act": 0.0
        },
        {
            "text": ".",
            "act": 0.0
        },
        {
            "text": ".",
            "act": 0.0
        },
        {
            "text": "By its nature it has to be,\" Roll said, adding that they were encouraged to live their lives as normally as possible.",
            "act": 0.0
        },
        {
            "text": "\"It was handled very professionally by the Marshals Service.\"",
            "act": 0.0
        },
        {
            "text": "At the end of the month, Roll said four key men had been identified as threat makers.",
            "act": 0.0
        },
        {
            "text": "The Marshals Service left to him the decision to press charges but recommended against it.",
            "act": 0.0
        },
        {
            "text": "Roll said he had no qualms about following their advice.",
            "act": 0.0
        },
        {
            "text": "AZ_Transplant\n\nI worked in her office last year.",
            "act": 0.0
        },
        {
            "text": "I only met her a few times, but she she was always really genuine and kind.",
            "act": 0.0
        },
        {
            "text": "I hope she pulls through.",
            "act": 0.0
        },
        {
            "text": "It's not a particularly common name, is it?",
            "act": 0.0
        },
        {
            "text": "Photo must be from 2010 festival, since the 2011 one is not scheduled until March.",
            "act": 0.0
        },
        {
            "text": "karen\n\nYeah that's what I was thinking.",
            "act": 0.0
        },
        {
            "text": "EdFlintstone\n\nSarah save your bullshit sympathy post on fucking facebook.",
            "act": 0.0
        }
    ]
}